catcher/__init__.py
catcher/_version.py
catcher/collector.py
catcher/tests.py
catcher/uploaders/__init__.py
catcher/uploaders/ajentiorg.py
catcher/uploaders/pastehtml.py
catcher/formatters/html.py
catcher/formatters/__init__.py
catcher/formatters/text.py
python_catcher-0.1.7.dist-info/metadata.json
python_catcher-0.1.7.dist-info/METADATA
python_catcher-0.1.7.dist-info/top_level.txt
python_catcher-0.1.7.dist-info/DESCRIPTION.rst
python_catcher-0.1.7.dist-info/WHEEL
python_catcher-0.1.7.dist-info/RECORD
