Metadata-Version: 2.0
Name: python-catcher
Version: 0.1.7
Summary: Beautiful stack traces for Python
Home-page: http://ajenti.org/
Author: Eugene Pankov
Author-email: e@ajenti.org
License: UNKNOWN
Platform: UNKNOWN
Requires-Dist: requests
Requires-Dist: Mako
